AUTHORS.md
setup.py
django_throttle.egg-info/PKG-INFO
django_throttle.egg-info/SOURCES.txt
django_throttle.egg-info/dependency_links.txt
django_throttle.egg-info/top_level.txt
throttle/__init__.py
throttle/decorators.py
throttle/models.py
throttle/tests.py
throttle/views.py