Metadata-Version: 1.1
Name: django-throttle
Version: 0.3.1
Summary: Simple application for throttling HTTP requests to views
Home-page: UNKNOWN
Author: marazmiki
Author-email: marazmiki@gmail.com
License: UNKNOWN
Platform: UNKNOWN
Classifier: Environment :: Web Environment
Classifier: Programming Language :: Python
Classifier: Framework :: Django
